MANIFEST.in
setup.cfg
setup.py
Marcellus.egg-info/PKG-INFO
Marcellus.egg-info/SOURCES.txt
Marcellus.egg-info/dependency_links.txt
Marcellus.egg-info/requires.txt
Marcellus.egg-info/top_level.txt
marcellus/__init__.py
marcellus/dataset.py
marcellus/dict.py
marcellus/ficherocsv.py
marcellus/sendmail.py
marcellus/util.py
marcellus/util2.py
marcellus/xlsreport.py
marcellus/postgres/__init__.py
marcellus/postgres/search.py
marcellus/templates/__init__.py
marcellus/templates/dstoxls.xml
marcellus/templates/test_auto_width.xml
marcellus/templates/test_image.xml
marcellus/templates/test_merge.xml
marcellus/templates/test_width.xml