Metadata-Version: 1.1
Name: Marcellus
Version: 1.0.1
Summary: Utilities for Quentin projects
Home-page: http://www.codevince.com
Author: León Domingo
Author-email: leon@codevince.dev
License: UNKNOWN
Keywords: marcellus codevince web
Platform: UNKNOWN
Classifier: Development Status :: 5 - Production/Stable
Classifier: Topic :: Utilities
